pytest_ordering.py
pytest_ordering/__init__.py
pytest_ordering/_version.py
pytest_ordering-0.4.dist-info/DESCRIPTION.rst
pytest_ordering-0.4.dist-info/entry_points.txt
pytest_ordering-0.4.dist-info/METADATA
pytest_ordering-0.4.dist-info/metadata.json
pytest_ordering-0.4.dist-info/RECORD
pytest_ordering-0.4.dist-info/top_level.txt
pytest_ordering-0.4.dist-info/WHEEL
